liberrpa/Application.py
liberrpa/Basic.py
liberrpa/Browser.py
liberrpa/Clipboard.py
liberrpa/Credential.py
liberrpa/Data.py
liberrpa/Database.py
liberrpa/Dialog.py
liberrpa/Dict.py
liberrpa/Excel.py
liberrpa/FTP.py
liberrpa/File.py
liberrpa/Keyboard.py
liberrpa/List.py
liberrpa/Logging.py
liberrpa/Mail.py
liberrpa/Math.py
liberrpa/Modules.py
liberrpa/Mouse.py
liberrpa/OCR.py
liberrpa/Outlook.py
liberrpa/Regex.py
liberrpa/ScreenPrint.py
liberrpa/Str.py
liberrpa/System.py
liberrpa/Time.py
liberrpa/Trigger.py
liberrpa/UiInterface.py
liberrpa/Web.py
liberrpa/Window.py
liberrpa/__init__.py
liberrpa/Common/_BasicConfig.py
liberrpa/Common/_Chrome.py
liberrpa/Common/_Exception.py
liberrpa/Common/_Initialization.py
liberrpa/Common/_TypedValue.py
liberrpa/Common/_WebSocket.py
liberrpa/Common/__init__.py
liberrpa/FlowControl/End.py
liberrpa/FlowControl/ProjectFlowInit.py
liberrpa/FlowControl/Run.py
liberrpa/FlowControl/Start.py
liberrpa/FlowControl/SubStart.py
liberrpa/FlowControl/_ProjectDict.py
liberrpa/FlowControl/__init__.py
liberrpa/UI/_CommonValue.py
liberrpa/UI/_Image.py
liberrpa/UI/_Notifier.py
liberrpa/UI/_Overlay.py
liberrpa/UI/_QtWorker.py
liberrpa/UI/_Queue.py
liberrpa/UI/_Screenshot.py
liberrpa/UI/_TerminableThread.py
liberrpa/UI/_UiAutomation.py
liberrpa/UI/_UiDict.py
liberrpa/UI/_UiElement.py
liberrpa/UI/__init__.py
liberrpa-0.2.0.dist-info/METADATA
liberrpa-0.2.0.dist-info/WHEEL
liberrpa-0.2.0.dist-info/top_level.txt
liberrpa-0.2.0.dist-info/RECORD
