Metadata-Version: 2.4
Name: liberrpa
Version: 0.2.0
Summary: The main Python module of LiberRPA. If you install it from pip, run the command first: conda install ipykernel pywin32 screeninfo pywinhook pyautogui pyqt pynput keyboard json5 psutil pypdf pathvalidate pillow python-mss flask flask-socketio requests python-socketio websocket-client pyperclip sqlalchemy psycopg2 pymysql pymssql oracledb pandas xlwings ftputil imapclient yagmail ffmpeg
Home-page: https://github.com/HUHARED/LiberRPA/tree/main/condaLibrary/liberrpa
Author: Jiyan Hu
License: AGPL-3.0
Classifier: Programming Language :: Python :: 3
Classifier: Programming Language :: Python :: 3.12
Classifier: License :: OSI Approved :: GNU Affero General Public License v3
Classifier: Environment :: Win32 (MS Windows)
Classifier: Operating System :: Microsoft :: Windows :: Windows 10
Classifier: Operating System :: Microsoft :: Windows :: Windows 11
Requires-Python: >=3.12
Requires-Dist: uiautomation
Requires-Dist: easyocr
Requires-Dist: pystray
Requires-Dist: pyzipper
Requires-Dist: PyMuPDF
Requires-Dist: mail-parser
Dynamic: author
Dynamic: classifier
Dynamic: home-page
Dynamic: license
Dynamic: requires-dist
Dynamic: requires-python
Dynamic: summary
